kivy_garden/drag_n_drop/__init__.py
kivy_garden/drag_n_drop/_version.py
kivy_garden/drag_n_drop/tests/test_import.py
kivy_garden.drag_n_drop-0.1.0.dist-info/AUTHORS.txt
kivy_garden.drag_n_drop-0.1.0.dist-info/LICENSE.txt
kivy_garden.drag_n_drop-0.1.0.dist-info/METADATA
kivy_garden.drag_n_drop-0.1.0.dist-info/WHEEL
kivy_garden.drag_n_drop-0.1.0.dist-info/top_level.txt
kivy_garden.drag_n_drop-0.1.0.dist-info/RECORD
