Metadata-Version: 2.1
Name: kivy-garden.drag-n-drop
Version: 0.1.0
Summary: Flower that can drag and drop widgets between Kivy layouts.
Home-page: https://github.com/kivy-garden/drag_n_drop
Author: Kivy
Author-email: kivy@kivy.org
License: UNKNOWN
Project-URL: Bug Reports, https://github.com/kivy-garden/drag_n_drop/issues
Project-URL: Source, https://github.com/kivy-garden/drag_n_drop
Keywords: Kivy kivy-garden
Platform: UNKNOWN
Classifier: Development Status :: 4 - Beta
Classifier: Intended Audience :: Developers
Classifier: Topic :: Software Development :: Libraries
Classifier: License :: OSI Approved :: MIT License
Classifier: Programming Language :: Python :: 3.5
Classifier: Programming Language :: Python :: 3.6
Classifier: Programming Language :: Python :: 3.7
Classifier: Programming Language :: Python :: 3.8
Provides-Extra: ci
Provides-Extra: dev
